README.rst
setup.py
django_rest_jwt_sso.egg-info/PKG-INFO
django_rest_jwt_sso.egg-info/SOURCES.txt
django_rest_jwt_sso.egg-info/dependency_links.txt
django_rest_jwt_sso.egg-info/requires.txt
django_rest_jwt_sso.egg-info/top_level.txt
rest_framework_jwt_sso/__init__.py
rest_framework_jwt_sso/settings.py
rest_framework_jwt_sso/test.py
rest_framework_jwt_sso/views.py
rest_framework_jwt_sso/edjwt/__init__.py
rest_framework_jwt_sso/edjwt/algorithm.py
rest_framework_jwt_sso/edjwt/api_edjwt.py