Metadata-Version: 1.1
Name: django-rest-jwt-sso
Version: 0.0.4
Summary: Yet another SSO solution for Django REST Framework
Home-page: https://github.com/iqueensu/django-rest-jwt-sso
Author: Somion
Author-email: calibur.tonyt@gmail.com
License: MIT License
Platform: UNKNOWN
Classifier: Development Status :: 1 - Planning
Classifier: Environment :: Web Environment
Classifier: Framework :: Django
Classifier: Framework :: Django :: 2.2
Classifier: Intended Audience :: Developers
Classifier: License :: OSI Approved :: MIT License
Classifier: Operating System :: OS Independent
Classifier: Programming Language :: Python
Classifier: Programming Language :: Python :: 3.6
Classifier: Topic :: Internet :: WWW/HTTP
Classifier: Topic :: Internet :: WWW/HTTP :: Session
Classifier: Topic :: Software Development :: Libraries :: Python Modules
